helloworldmatheus/__init__.py
helloworldmatheus/helloworldmatheus.py
helloworldmatheus-0.0.1.dist-info/METADATA
helloworldmatheus-0.0.1.dist-info/WHEEL
helloworldmatheus-0.0.1.dist-info/top_level.txt
helloworldmatheus-0.0.1.dist-info/RECORD
