Metadata-Version: 2.4
Name: helloworldmatheus
Version: 0.0.1
Summary: teste
Home-page: https://github.com/Matheus-Fernandes21/simple-package-template.git
Author: matheusfernandes21
Author-email: mhtzeera@gmail.com
Requires-Python: >=3.8
Dynamic: author
Dynamic: author-email
Dynamic: description
Dynamic: description-content-type
Dynamic: home-page
Dynamic: requires-python
Dynamic: summary
